Guidewd/__init__.py
Guidewd/analyze_sitemap.py
Guidewd/main.py
Guidewd/streamlit_app.py
guidewd_sitemap_seo_tool-0.1.0.dist-info/licenses/LICENSE.txt
guidewd_sitemap_seo_tool-0.1.0.dist-info/METADATA
guidewd_sitemap_seo_tool-0.1.0.dist-info/WHEEL
guidewd_sitemap_seo_tool-0.1.0.dist-info/entry_points.txt
guidewd_sitemap_seo_tool-0.1.0.dist-info/top_level.txt
guidewd_sitemap_seo_tool-0.1.0.dist-info/RECORD
