Metadata-Version: 2.4
Name: guidewd-sitemap-seo-tool
Version: 0.1.0
Summary: Analyze sitemap XML files for SEO optimization with suggestions using Streamlit.
Home-page: https://github.com/yourusername/guidewd-sitemap-seo-tool
Author: Purva Tijare
Author-email: your-email@example.com
Classifier: Programming Language :: Python :: 3
Classifier: License :: OSI Approved :: MIT License
Classifier: Operating System :: OS Independent
Requires-Python: >=3.6
License-File: LICENSE.txt
Requires-Dist: requests
Requires-Dist: streamlit
Dynamic: author
Dynamic: author-email
Dynamic: classifier
Dynamic: description
Dynamic: description-content-type
Dynamic: home-page
Dynamic: license-file
Dynamic: requires-dist
Dynamic: requires-python
Dynamic: summary
